.flake8
.readthedocs.yaml
CHANGELOG.md
LICENSE.md
MANIFEST.in
README.md
README_pypi.md
pyproject.toml
pytest.ini
setup.py
PyThea/PyThea_app.py
PyThea/__init__.py
PyThea/_version.py
PyThea/callbacks.py
PyThea/geometrical_models.py
PyThea/modules.py
PyThea/pythea_cli.py
PyThea/utils.py
PyThea/utils_database.py
PyThea/version.py
PyThea.egg-info/.DS_Store
PyThea.egg-info/PKG-INFO
PyThea.egg-info/SOURCES.txt
PyThea.egg-info/dependency_links.txt
PyThea.egg-info/entry_points.txt
PyThea.egg-info/not-zip-safe
PyThea.egg-info/requires.txt
PyThea.egg-info/top_level.txt
PyThea/config/__init__.py
PyThea/config/app_styles.py
PyThea/config/config_sliders.py
PyThea/config/selected_bodies.py
PyThea/config/selected_imagers.py
PyThea/data/__init__.py
PyThea/data/sample_data.py
PyThea/extensions/LICENSE_gcs_python.md
PyThea/extensions/__init__.py
PyThea/extensions/buttons.py
PyThea/extensions/Parker_spirals/__init__.py
PyThea/extensions/Parker_spirals/utils.py
PyThea/extensions/hek/__init__.py
PyThea/extensions/hek/utils.py
PyThea/sunpy_dev/__init__.py
PyThea/sunpy_dev/extern/__init__.py
PyThea/sunpy_dev/extern/sunkit_instruments/__init__.py
PyThea/sunpy_dev/extern/sunkit_instruments/aia/__init__.py
PyThea/sunpy_dev/extern/sunkit_instruments/aia/utils.py
PyThea/sunpy_dev/extern/sunkit_instruments/lasco/__init__.py
PyThea/sunpy_dev/extern/sunkit_instruments/lasco/utils.py
PyThea/sunpy_dev/extern/sunkit_instruments/stereo/__init__.py
PyThea/sunpy_dev/extern/sunkit_instruments/stereo/utils.py
PyThea/sunpy_dev/map/__init__.py
PyThea/sunpy_dev/map/maputils.py
PyThea/test/Pythea_test.py
PyThea/test/__init__.py
PyThea/test/conftest.py
PyThea/test/figure_hashes.json
PyThea/test/test_extension_utils.py
PyThea/test/test_figures.py
PyThea/test/test_geometrical_models.py
PyThea/test/test_imports.py
PyThea/test/test_remote_clients.py
PyThea/test/test_utils.py