Metadata-Version: 2.4
Name: PyThea
Version: 1.2.0
Summary: PyThea: A software package to reconstruct the 3D structure of CMEs and shock waves
Author-email: Athanasios Kouloumvakos <athkouloumvakos@gmail.com>
License: 
Project-URL: Homepage, https://www.pythea.org
Project-URL: Documentation, https://www.pythea.org/en/latest/
Project-URL: Source Code, https://github.com/AthKouloumvakos/PyThea
Project-URL: Download, https://pypi.org/project/PyThea
Keywords: science,solar physics,solar,coronal mass ejections,shock waves,EUV waves
Platform: any
Classifier: Programming Language :: Python
Classifier: Programming Language :: Python :: 3
Classifier: Programming Language :: Python :: 3.11
Classifier: Development Status :: 5 - Production/Stable
Classifier: License :: OSI Approved :: GNU General Public License v3 (GPLv3)
Classifier: Operating System :: OS Independent
Classifier: Intended Audience :: Science/Research
Classifier: Topic :: Scientific/Engineering :: Physics
Provides: PyThea
Requires-Python: >=3.11
License-File: LICENSE.md
Requires-Dist: sunpy>=7.0.1
Requires-Dist: pandas
Requires-Dist: scipy
Requires-Dist: matplotlib
Requires-Dist: aiapy
Requires-Dist: numexpr
Requires-Dist: streamlit
Requires-Dist: seaborn
Requires-Dist: pyvista
Requires-Dist: sunpy_soar
Provides-Extra: all
Requires-Dist: pythea; extra == "all"
Provides-Extra: tests
Requires-Dist: jplephem; extra == "tests"
Requires-Dist: pooch; extra == "tests"
Requires-Dist: pytest; extra == "tests"
Requires-Dist: pytest-astropy; extra == "tests"
Requires-Dist: pytest-sugar; extra == "tests"
Requires-Dist: pytest-mpl; extra == "tests"
Provides-Extra: docs
Requires-Dist: pooch; extra == "docs"
Requires-Dist: plotly; extra == "docs"
Requires-Dist: jplephem; extra == "docs"
Requires-Dist: sphinx>=6.0.0; extra == "docs"
Requires-Dist: sphinx-automodapi; extra == "docs"
Requires-Dist: sphinx-gallery; extra == "docs"
Requires-Dist: jupyter_sphinx; extra == "docs"
Requires-Dist: sphinx-rtd-theme; extra == "docs"
Requires-Dist: numpydoc; extra == "docs"
Dynamic: license-file
